pyiron_gui/__init__.py
pyiron_gui/_version.py
pyiron_gui/monkey_patching.py
pyiron_gui/project/__init__.py
pyiron_gui/project/project.py
pyiron_gui/project/project_browser.py
pyiron_gui/utils/__init__.py
pyiron_gui/utils/decorators.py
pyiron_gui/widgets/__init__.py
pyiron_gui/widgets/widgets.py
pyiron_gui/wrapper/__init__.py
pyiron_gui/wrapper/widgets.py
pyiron_gui/wrapper/wrapper.py
pyiron_gui-0.0.12.dist-info/LICENSE
pyiron_gui-0.0.12.dist-info/METADATA
pyiron_gui-0.0.12.dist-info/WHEEL
pyiron_gui-0.0.12.dist-info/top_level.txt
pyiron_gui-0.0.12.dist-info/RECORD
